{
	"$schema": "http://schema.management.azure.com/schemas/2015-01-01/deploymentTemplate.json#",
	"contentVersion": "1.0.0.0",
	"parameters": {
		"factoryName": {
			"type": "string",
			"metadata": "Data Factory name",
			"defaultValue": "azr-data-fact-1"
		},
		"AzureBlobStorage1_connectionString": {
			"type": "secureString",
			"metadata": "Secure string for 'connectionString' of 'AzureBlobStorage1'"
		},
		"AzureSqlDatabase1_connectionString": {
			"type": "secureString",
			"metadata": "Secure string for 'connectionString' of 'AzureSqlDatabase1'"
		},
		"linkedservice1_connectionString": {
			"type": "secureString",
			"metadata": "Secure string for 'connectionString' of 'linkedservice1'"
		}
	},
	"variables": {
		"factoryId": "[concat('Microsoft.DataFactory/factories/', parameters('factoryName'))]"
	},
	"resources": [
		{
			"name": "[concat(parameters('factoryName'), '/AzureBlobStorage1')]",
			"type": "Microsoft.DataFactory/factories/linkedServices",
			"apiVersion": "2018-06-01",
			"properties": {
				"annotations": [],
				"type": "AzureBlobStorage",
				"typeProperties": {
					"connectionString": "[parameters('AzureBlobStorage1_connectionString')]"
				}
			},
			"dependsOn": []
		},
		{
			"name": "[concat(parameters('factoryName'), '/AzureSqlDatabase1')]",
			"type": "Microsoft.DataFactory/factories/linkedServices",
			"apiVersion": "2018-06-01",
			"properties": {
				"annotations": [],
				"type": "AzureSqlDatabase",
				"typeProperties": {
					"connectionString": "[parameters('AzureSqlDatabase1_connectionString')]"
				}
			},
			"dependsOn": []
		},
		{
			"name": "[concat(parameters('factoryName'), '/linkedservice1')]",
			"type": "Microsoft.DataFactory/factories/linkedServices",
			"apiVersion": "2018-06-01",
			"properties": {
				"annotations": [],
				"type": "AzureBlobStorage",
				"typeProperties": {
					"connectionString": "[parameters('linkedservice1_connectionString')]"
				}
			},
			"dependsOn": []
		},
		{
			"name": "[concat(parameters('factoryName'), '/Archive')]",
			"type": "Microsoft.DataFactory/factories/datasets",
			"apiVersion": "2018-06-01",
			"properties": {
				"linkedServiceName": {
					"referenceName": "AzureBlobStorage1",
					"type": "LinkedServiceReference"
				},
				"annotations": [],
				"type": "Binary",
				"typeProperties": {
					"location": {
						"type": "AzureBlobStorageLocation",
						"folderPath": "archive",
						"container": "adlsconacc1"
					}
				}
			},
			"dependsOn": [
				"[concat(variables('factoryId'), '/linkedServices/AzureBlobStorage1')]"
			]
		},
		{
			"name": "[concat(parameters('factoryName'), '/AzureSqlTable1')]",
			"type": "Microsoft.DataFactory/factories/datasets",
			"apiVersion": "2018-06-01",
			"properties": {
				"linkedServiceName": {
					"referenceName": "AzureSqlDatabase1",
					"type": "LinkedServiceReference"
				},
				"annotations": [],
				"type": "AzureSqlTable",
				"schema": [
					{
						"name": "Name",
						"type": "nvarchar"
					},
					{
						"name": "Age",
						"type": "nvarchar"
					},
					{
						"name": "Gender",
						"type": "nvarchar"
					}
				],
				"typeProperties": {
					"schema": "mydb1",
					"table": "employee2"
				}
			},
			"dependsOn": [
				"[concat(variables('factoryId'), '/linkedServices/AzureSqlDatabase1')]"
			]
		},
		{
			"name": "[concat(parameters('factoryName'), '/Binary1')]",
			"type": "Microsoft.DataFactory/factories/datasets",
			"apiVersion": "2018-06-01",
			"properties": {
				"linkedServiceName": {
					"referenceName": "linkedservice1",
					"type": "LinkedServiceReference"
				},
				"parameters": {
					"filename": {
						"type": "string"
					}
				},
				"annotations": [],
				"type": "Binary",
				"typeProperties": {
					"location": {
						"type": "AzureBlobStorageLocation",
						"fileName": {
							"value": "@dataset().filename",
							"type": "Expression"
						},
						"folderPath": "input",
						"container": "adlsconacc1"
					},
					"compression": {
						"type": "ZipDeflate",
						"level": "Optimal"
					}
				}
			},
			"dependsOn": [
				"[concat(variables('factoryId'), '/linkedServices/linkedservice1')]"
			]
		},
		{
			"name": "[concat(parameters('factoryName'), '/Binary2')]",
			"type": "Microsoft.DataFactory/factories/datasets",
			"apiVersion": "2018-06-01",
			"properties": {
				"linkedServiceName": {
					"referenceName": "AzureBlobStorage1",
					"type": "LinkedServiceReference"
				},
				"annotations": [],
				"type": "Binary",
				"typeProperties": {
					"location": {
						"type": "AzureBlobStorageLocation",
						"folderPath": "output",
						"container": "adlsconacc1"
					}
				}
			},
			"dependsOn": [
				"[concat(variables('factoryId'), '/linkedServices/AzureBlobStorage1')]"
			]
		},
		{
			"name": "[concat(parameters('factoryName'), '/Binary3')]",
			"type": "Microsoft.DataFactory/factories/datasets",
			"apiVersion": "2018-06-01",
			"properties": {
				"linkedServiceName": {
					"referenceName": "AzureBlobStorage1",
					"type": "LinkedServiceReference"
				},
				"parameters": {
					"file": {
						"type": "string"
					}
				},
				"annotations": [],
				"type": "Binary",
				"typeProperties": {
					"location": {
						"type": "AzureBlobStorageLocation",
						"fileName": {
							"value": "@dataset().file",
							"type": "Expression"
						},
						"folderPath": "input",
						"container": "adlsconacc1"
					}
				}
			},
			"dependsOn": [
				"[concat(variables('factoryId'), '/linkedServices/AzureBlobStorage1')]"
			]
		},
		{
			"name": "[concat(parameters('factoryName'), '/Binary4')]",
			"type": "Microsoft.DataFactory/factories/datasets",
			"apiVersion": "2018-06-01",
			"properties": {
				"linkedServiceName": {
					"referenceName": "AzureBlobStorage1",
					"type": "LinkedServiceReference"
				},
				"annotations": [],
				"type": "Binary",
				"typeProperties": {
					"location": {
						"type": "AzureBlobStorageLocation",
						"folderPath": "archive",
						"container": "adlsconacc1"
					}
				}
			},
			"dependsOn": [
				"[concat(variables('factoryId'), '/linkedServices/AzureBlobStorage1')]"
			]
		},
		{
			"name": "[concat(parameters('factoryName'), '/DelimitedText1')]",
			"type": "Microsoft.DataFactory/factories/datasets",
			"apiVersion": "2018-06-01",
			"properties": {
				"linkedServiceName": {
					"referenceName": "AzureBlobStorage1",
					"type": "LinkedServiceReference"
				},
				"annotations": [],
				"type": "DelimitedText",
				"typeProperties": {
					"location": {
						"type": "AzureBlobStorageLocation",
						"folderPath": "output",
						"container": "adlsconacc1"
					},
					"columnDelimiter": ",",
					"escapeChar": "\\",
					"firstRowAsHeader": true,
					"quoteChar": "\""
				},
				"schema": [
					{
						"name": "Name",
						"type": "String"
					},
					{
						"name": "Age",
						"type": "String"
					},
					{
						"name": "Gender",
						"type": "String"
					}
				]
			},
			"dependsOn": [
				"[concat(variables('factoryId'), '/linkedServices/AzureBlobStorage1')]"
			]
		},
		{
			"name": "[concat(parameters('factoryName'), '/DestinationDataset_5np')]",
			"type": "Microsoft.DataFactory/factories/datasets",
			"apiVersion": "2018-06-01",
			"properties": {
				"linkedServiceName": {
					"referenceName": "AzureSqlDatabase1",
					"type": "LinkedServiceReference"
				},
				"annotations": [],
				"type": "AzureSqlTable",
				"schema": [],
				"typeProperties": {
					"schema": "mydb1",
					"table": "employee"
				}
			},
			"dependsOn": [
				"[concat(variables('factoryId'), '/linkedServices/AzureSqlDatabase1')]"
			]
		},
		{
			"name": "[concat(parameters('factoryName'), '/DestinationDataset_i3q')]",
			"type": "Microsoft.DataFactory/factories/datasets",
			"apiVersion": "2018-06-01",
			"properties": {
				"linkedServiceName": {
					"referenceName": "AzureSqlDatabase1",
					"type": "LinkedServiceReference"
				},
				"annotations": [],
				"type": "AzureSqlTable",
				"schema": [],
				"typeProperties": {
					"schema": "mydb1",
					"table": "employee"
				}
			},
			"dependsOn": [
				"[concat(variables('factoryId'), '/linkedServices/AzureSqlDatabase1')]"
			]
		},
		{
			"name": "[concat(parameters('factoryName'), '/SourceDataset_5np')]",
			"type": "Microsoft.DataFactory/factories/datasets",
			"apiVersion": "2018-06-01",
			"properties": {
				"linkedServiceName": {
					"referenceName": "AzureBlobStorage1",
					"type": "LinkedServiceReference"
				},
				"annotations": [],
				"type": "DelimitedText",
				"typeProperties": {
					"location": {
						"type": "AzureBlobStorageLocation",
						"folderPath": "output",
						"container": "adlsconacc1"
					},
					"columnDelimiter": ",",
					"escapeChar": "\\",
					"firstRowAsHeader": true,
					"quoteChar": "\""
				},
				"schema": [
					{
						"name": "Name",
						"type": "String"
					},
					{
						"name": "Age",
						"type": "String"
					},
					{
						"name": "Gender",
						"type": "String"
					}
				]
			},
			"dependsOn": [
				"[concat(variables('factoryId'), '/linkedServices/AzureBlobStorage1')]"
			]
		},
		{
			"name": "[concat(parameters('factoryName'), '/SourceDataset_i3q')]",
			"type": "Microsoft.DataFactory/factories/datasets",
			"apiVersion": "2018-06-01",
			"properties": {
				"linkedServiceName": {
					"referenceName": "AzureBlobStorage1",
					"type": "LinkedServiceReference"
				},
				"annotations": [],
				"type": "DelimitedText",
				"typeProperties": {
					"location": {
						"type": "AzureBlobStorageLocation",
						"fileName": "employee_1.csv",
						"folderPath": "output",
						"container": "adlsconacc1"
					},
					"columnDelimiter": ",",
					"escapeChar": "\\",
					"firstRowAsHeader": true,
					"quoteChar": "\""
				},
				"schema": [
					{
						"name": "Name",
						"type": "String"
					},
					{
						"name": "Age",
						"type": "String"
					},
					{
						"name": "Gender",
						"type": "String"
					}
				]
			},
			"dependsOn": [
				"[concat(variables('factoryId'), '/linkedServices/AzureBlobStorage1')]"
			]
		},
		{
			"name": "[concat(parameters('factoryName'), '/CopyPipeline_5np')]",
			"type": "Microsoft.DataFactory/factories/pipelines",
			"apiVersion": "2018-06-01",
			"properties": {
				"activities": [
					{
						"name": "Copy_5np",
						"type": "Copy",
						"dependsOn": [],
						"policy": {
							"timeout": "7.00:00:00",
							"retry": 0,
							"retryIntervalInSeconds": 30,
							"secureOutput": false,
							"secureInput": false
						},
						"userProperties": [
							{
								"name": "Source",
								"value": "adlsconacc1/output/"
							},
							{
								"name": "Destination",
								"value": "mydb1.employee"
							}
						],
						"typeProperties": {
							"source": {
								"type": "DelimitedTextSource",
								"storeSettings": {
									"type": "AzureBlobStorageReadSettings",
									"recursive": true,
									"wildcardFileName": "*",
									"enablePartitionDiscovery": false
								},
								"formatSettings": {
									"type": "DelimitedTextReadSettings",
									"skipLineCount": 0
								}
							},
							"sink": {
								"type": "AzureSqlSink",
								"tableOption": "autoCreate"
							},
							"enableStaging": false,
							"validateDataConsistency": false,
							"translator": {
								"type": "TabularTranslator",
								"mappings": [
									{
										"source": {
											"name": "Name",
											"type": "String",
											"physicalType": "String"
										},
										"sink": {
											"name": "Name",
											"type": "String"
										}
									},
									{
										"source": {
											"name": "Age",
											"type": "String",
											"physicalType": "String"
										},
										"sink": {
											"name": "Age",
											"type": "String"
										}
									},
									{
										"source": {
											"name": "Gender",
											"type": "String",
											"physicalType": "String"
										},
										"sink": {
											"name": "Gender",
											"type": "String"
										}
									}
								],
								"typeConversion": true,
								"typeConversionSettings": {
									"allowDataTruncation": true,
									"treatBooleanAsNumber": false
								}
							}
						},
						"inputs": [
							{
								"referenceName": "SourceDataset_5np",
								"type": "DatasetReference",
								"parameters": {}
							}
						],
						"outputs": [
							{
								"referenceName": "DestinationDataset_5np",
								"type": "DatasetReference",
								"parameters": {}
							}
						]
					}
				],
				"annotations": []
			},
			"dependsOn": [
				"[concat(variables('factoryId'), '/datasets/SourceDataset_5np')]",
				"[concat(variables('factoryId'), '/datasets/DestinationDataset_5np')]"
			]
		},
		{
			"name": "[concat(parameters('factoryName'), '/CopyPipeline_i3q')]",
			"type": "Microsoft.DataFactory/factories/pipelines",
			"apiVersion": "2018-06-01",
			"properties": {
				"activities": [
					{
						"name": "Copy_i3q",
						"type": "Copy",
						"dependsOn": [],
						"policy": {
							"timeout": "7.00:00:00",
							"retry": 0,
							"retryIntervalInSeconds": 30,
							"secureOutput": false,
							"secureInput": false
						},
						"userProperties": [
							{
								"name": "Source",
								"value": "adlsconacc1/output/employee_1.csv"
							},
							{
								"name": "Destination",
								"value": "mydb1.employee"
							}
						],
						"typeProperties": {
							"source": {
								"type": "DelimitedTextSource",
								"storeSettings": {
									"type": "AzureBlobStorageReadSettings",
									"recursive": true,
									"enablePartitionDiscovery": false
								},
								"formatSettings": {
									"type": "DelimitedTextReadSettings",
									"skipLineCount": 0
								}
							},
							"sink": {
								"type": "AzureSqlSink",
								"tableOption": "autoCreate"
							},
							"enableStaging": false,
							"validateDataConsistency": false,
							"translator": {
								"type": "TabularTranslator",
								"mappings": [
									{
										"source": {
											"name": "Name",
											"type": "String",
											"physicalType": "String"
										},
										"sink": {
											"name": "Name",
											"type": "String"
										}
									},
									{
										"source": {
											"name": "Age",
											"type": "String",
											"physicalType": "String"
										},
										"sink": {
											"name": "Age",
											"type": "String"
										}
									},
									{
										"source": {
											"name": "Gender",
											"type": "String",
											"physicalType": "String"
										},
										"sink": {
											"name": "Gender",
											"type": "String"
										}
									}
								],
								"typeConversion": true,
								"typeConversionSettings": {
									"allowDataTruncation": true,
									"treatBooleanAsNumber": false
								}
							}
						},
						"inputs": [
							{
								"referenceName": "SourceDataset_i3q",
								"type": "DatasetReference",
								"parameters": {}
							}
						],
						"outputs": [
							{
								"referenceName": "DestinationDataset_i3q",
								"type": "DatasetReference",
								"parameters": {}
							}
						]
					}
				],
				"annotations": []
			},
			"dependsOn": [
				"[concat(variables('factoryId'), '/datasets/SourceDataset_i3q')]",
				"[concat(variables('factoryId'), '/datasets/DestinationDataset_i3q')]"
			]
		},
		{
			"name": "[concat(parameters('factoryName'), '/pipeline1')]",
			"type": "Microsoft.DataFactory/factories/pipelines",
			"apiVersion": "2018-06-01",
			"properties": {
				"activities": [
					{
						"name": "Get Metadata1",
						"type": "GetMetadata",
						"dependsOn": [],
						"policy": {
							"timeout": "7.00:00:00",
							"retry": 0,
							"retryIntervalInSeconds": 30,
							"secureOutput": false,
							"secureInput": false
						},
						"userProperties": [],
						"typeProperties": {
							"dataset": {
								"referenceName": "Binary1",
								"type": "DatasetReference",
								"parameters": {
									"filename": "*.zip"
								}
							},
							"fieldList": [
								"itemType"
							],
							"storeSettings": {
								"type": "AzureBlobStorageReadSettings",
								"recursive": true,
								"enablePartitionDiscovery": false
							},
							"formatSettings": {
								"type": "BinaryReadSettings"
							}
						}
					},
					{
						"name": "ForEach1",
						"type": "ForEach",
						"dependsOn": [
							{
								"activity": "Get Metadata1",
								"dependencyConditions": [
									"Succeeded"
								]
							}
						],
						"userProperties": [],
						"typeProperties": {
							"items": {
								"value": "@activity('Get Metadata1').output.childitems",
								"type": "Expression"
							},
							"activities": [
								{
									"name": "Copy data1",
									"type": "Copy",
									"dependsOn": [],
									"policy": {
										"timeout": "7.00:00:00",
										"retry": 0,
										"retryIntervalInSeconds": 30,
										"secureOutput": false,
										"secureInput": false
									},
									"userProperties": [],
									"typeProperties": {
										"source": {
											"type": "BinarySource",
											"storeSettings": {
												"type": "AzureBlobStorageReadSettings",
												"recursive": false,
												"deleteFilesAfterCompletion": false
											},
											"formatSettings": {
												"type": "BinaryReadSettings",
												"compressionProperties": {
													"type": "ZipDeflateReadSettings",
													"preserveZipFileNameAsFolder": false
												}
											}
										},
										"sink": {
											"type": "BinarySink",
											"storeSettings": {
												"type": "AzureBlobStorageWriteSettings",
												"copyBehavior": "FlattenHierarchy"
											}
										},
										"enableStaging": false
									},
									"inputs": [
										{
											"referenceName": "Binary1",
											"type": "DatasetReference",
											"parameters": {
												"filename": "@item().name"
											}
										}
									],
									"outputs": [
										{
											"referenceName": "Binary2",
											"type": "DatasetReference",
											"parameters": {}
										}
									]
								}
							]
						}
					}
				],
				"annotations": []
			},
			"dependsOn": [
				"[concat(variables('factoryId'), '/datasets/Binary1')]",
				"[concat(variables('factoryId'), '/datasets/Binary2')]"
			]
		},
		{
			"name": "[concat(parameters('factoryName'), '/pipeline2')]",
			"type": "Microsoft.DataFactory/factories/pipelines",
			"apiVersion": "2018-06-01",
			"properties": {
				"activities": [
					{
						"name": "Get Metadata1",
						"type": "GetMetadata",
						"dependsOn": [],
						"policy": {
							"timeout": "7.00:00:00",
							"retry": 0,
							"retryIntervalInSeconds": 30,
							"secureOutput": false,
							"secureInput": false
						},
						"userProperties": [],
						"typeProperties": {
							"dataset": {
								"referenceName": "Binary1",
								"type": "DatasetReference",
								"parameters": {
									"filename": {
										"value": "*.zip",
										"type": "Expression"
									}
								}
							},
							"fieldList": [
								"childItems"
							],
							"storeSettings": {
								"type": "AzureBlobStorageReadSettings",
								"recursive": true,
								"enablePartitionDiscovery": false
							},
							"formatSettings": {
								"type": "BinaryReadSettings"
							}
						}
					},
					{
						"name": "ForEach1",
						"type": "ForEach",
						"dependsOn": [
							{
								"activity": "Get Metadata1",
								"dependencyConditions": [
									"Succeeded"
								]
							}
						],
						"userProperties": [],
						"typeProperties": {
							"items": {
								"value": "@activity('Get Metadata1').output.childitems",
								"type": "Expression"
							},
							"activities": [
								{
									"name": "Copy data1",
									"type": "Copy",
									"dependsOn": [],
									"policy": {
										"timeout": "7.00:00:00",
										"retry": 0,
										"retryIntervalInSeconds": 30,
										"secureOutput": false,
										"secureInput": false
									},
									"userProperties": [],
									"typeProperties": {
										"source": {
											"type": "BinarySource",
											"storeSettings": {
												"type": "AzureBlobStorageReadSettings",
												"recursive": false,
												"deleteFilesAfterCompletion": false
											},
											"formatSettings": {
												"type": "BinaryReadSettings",
												"compressionProperties": {
													"type": "ZipDeflateReadSettings",
													"preserveZipFileNameAsFolder": false
												}
											}
										},
										"sink": {
											"type": "BinarySink",
											"storeSettings": {
												"type": "AzureBlobStorageWriteSettings"
											}
										},
										"enableStaging": false
									},
									"inputs": [
										{
											"referenceName": "Binary1",
											"type": "DatasetReference",
											"parameters": {
												"filename": {
													"value": "@item().name",
													"type": "Expression"
												}
											}
										}
									],
									"outputs": [
										{
											"referenceName": "Binary2",
											"type": "DatasetReference",
											"parameters": {}
										}
									]
								}
							]
						}
					},
					{
						"name": "Copy data2",
						"type": "Copy",
						"dependsOn": [
							{
								"activity": "ForEach1",
								"dependencyConditions": [
									"Succeeded"
								]
							}
						],
						"policy": {
							"timeout": "7.00:00:00",
							"retry": 0,
							"retryIntervalInSeconds": 30,
							"secureOutput": false,
							"secureInput": false
						},
						"userProperties": [],
						"typeProperties": {
							"source": {
								"type": "DelimitedTextSource",
								"storeSettings": {
									"type": "AzureBlobStorageReadSettings",
									"recursive": true,
									"wildcardFolderPath": "output",
									"wildcardFileName": "*.csv",
									"enablePartitionDiscovery": false
								},
								"formatSettings": {
									"type": "DelimitedTextReadSettings"
								}
							},
							"sink": {
								"type": "AzureSqlSink"
							},
							"enableStaging": false,
							"translator": {
								"type": "TabularTranslator",
								"mappings": [
									{
										"source": {
											"name": "Name",
											"type": "String",
											"physicalType": "String"
										},
										"sink": {
											"name": "Name",
											"type": "String",
											"physicalType": "nvarchar"
										}
									},
									{
										"source": {
											"name": "Age",
											"type": "String",
											"physicalType": "String"
										},
										"sink": {
											"name": "Age",
											"type": "String",
											"physicalType": "nvarchar"
										}
									},
									{
										"source": {
											"name": "Gender",
											"type": "String",
											"physicalType": "String"
										},
										"sink": {
											"name": "Gender",
											"type": "String",
											"physicalType": "nvarchar"
										}
									}
								],
								"typeConversion": true,
								"typeConversionSettings": {
									"allowDataTruncation": true,
									"treatBooleanAsNumber": false
								}
							}
						},
						"inputs": [
							{
								"referenceName": "DelimitedText1",
								"type": "DatasetReference",
								"parameters": {}
							}
						],
						"outputs": [
							{
								"referenceName": "AzureSqlTable1",
								"type": "DatasetReference",
								"parameters": {}
							}
						]
					},
					{
						"name": "Get Metadata2",
						"type": "GetMetadata",
						"dependsOn": [
							{
								"activity": "Copy data2",
								"dependencyConditions": [
									"Succeeded"
								]
							}
						],
						"policy": {
							"timeout": "7.00:00:00",
							"retry": 0,
							"retryIntervalInSeconds": 30,
							"secureOutput": false,
							"secureInput": false
						},
						"userProperties": [],
						"typeProperties": {
							"dataset": {
								"referenceName": "Binary3",
								"type": "DatasetReference",
								"parameters": {
									"file": "*.zip"
								}
							},
							"fieldList": [
								"childItems"
							],
							"storeSettings": {
								"type": "AzureBlobStorageReadSettings",
								"recursive": true,
								"enablePartitionDiscovery": false
							},
							"formatSettings": {
								"type": "BinaryReadSettings"
							}
						}
					},
					{
						"name": "Filter1",
						"type": "Filter",
						"dependsOn": [
							{
								"activity": "Get Metadata2",
								"dependencyConditions": [
									"Succeeded"
								]
							}
						],
						"userProperties": [],
						"typeProperties": {
							"items": {
								"value": "@activity('Get Metadata2').output.childitems",
								"type": "Expression"
							},
							"condition": {
								"value": "@endswith(item().name,'.zip')",
								"type": "Expression"
							}
						}
					},
					{
						"name": "ForEach2",
						"type": "ForEach",
						"dependsOn": [
							{
								"activity": "Filter1",
								"dependencyConditions": [
									"Succeeded"
								]
							}
						],
						"userProperties": [],
						"typeProperties": {
							"items": {
								"value": "@activity('Filter1').output.Value",
								"type": "Expression"
							},
							"activities": [
								{
									"name": "Copy data3",
									"type": "Copy",
									"dependsOn": [],
									"policy": {
										"timeout": "7.00:00:00",
										"retry": 0,
										"retryIntervalInSeconds": 30,
										"secureOutput": false,
										"secureInput": false
									},
									"userProperties": [],
									"typeProperties": {
										"source": {
											"type": "BinarySource",
											"storeSettings": {
												"type": "AzureBlobStorageReadSettings",
												"recursive": true,
												"deleteFilesAfterCompletion": false
											},
											"formatSettings": {
												"type": "BinaryReadSettings",
												"compressionProperties": {
													"type": "ZipDeflateReadSettings"
												}
											}
										},
										"sink": {
											"type": "BinarySink",
											"storeSettings": {
												"type": "AzureBlobStorageWriteSettings"
											}
										},
										"enableStaging": false
									},
									"inputs": [
										{
											"referenceName": "Binary1",
											"type": "DatasetReference",
											"parameters": {
												"filename": "@item().name"
											}
										}
									],
									"outputs": [
										{
											"referenceName": "Archive",
											"type": "DatasetReference",
											"parameters": {}
										}
									]
								},
								{
									"name": "Delete1",
									"type": "Delete",
									"dependsOn": [
										{
											"activity": "Copy data3",
											"dependencyConditions": [
												"Succeeded"
											]
										}
									],
									"policy": {
										"timeout": "7.00:00:00",
										"retry": 0,
										"retryIntervalInSeconds": 30,
										"secureOutput": false,
										"secureInput": false
									},
									"userProperties": [],
									"typeProperties": {
										"dataset": {
											"referenceName": "Binary1",
											"type": "DatasetReference",
											"parameters": {
												"filename": "@item().name"
											}
										},
										"logStorageSettings": {
											"linkedServiceName": {
												"referenceName": "AzureBlobStorage1",
												"type": "LinkedServiceReference"
											},
											"path": "adlsconacc1"
										},
										"enableLogging": true,
										"storeSettings": {
											"type": "AzureBlobStorageReadSettings",
											"recursive": true,
											"enablePartitionDiscovery": false
										}
									}
								}
							]
						}
					}
				],
				"annotations": []
			},
			"dependsOn": [
				"[concat(variables('factoryId'), '/datasets/Binary1')]",
				"[concat(variables('factoryId'), '/datasets/DelimitedText1')]",
				"[concat(variables('factoryId'), '/datasets/AzureSqlTable1')]",
				"[concat(variables('factoryId'), '/datasets/Binary3')]",
				"[concat(variables('factoryId'), '/datasets/Binary2')]",
				"[concat(variables('factoryId'), '/datasets/Archive')]",
				"[concat(variables('factoryId'), '/linkedServices/AzureBlobStorage1')]"
			]
		},
		{
			"name": "[concat(parameters('factoryName'), '/pipeline2_copy1')]",
			"type": "Microsoft.DataFactory/factories/pipelines",
			"apiVersion": "2018-06-01",
			"properties": {
				"activities": [
					{
						"name": "Get Metadata1",
						"type": "GetMetadata",
						"dependsOn": [],
						"policy": {
							"timeout": "7.00:00:00",
							"retry": 0,
							"retryIntervalInSeconds": 30,
							"secureOutput": false,
							"secureInput": false
						},
						"userProperties": [],
						"typeProperties": {
							"dataset": {
								"referenceName": "Binary1",
								"type": "DatasetReference",
								"parameters": {
									"filename": {
										"value": "*.zip",
										"type": "Expression"
									}
								}
							},
							"fieldList": [
								"childItems"
							],
							"storeSettings": {
								"type": "AzureBlobStorageReadSettings",
								"recursive": true,
								"enablePartitionDiscovery": false
							},
							"formatSettings": {
								"type": "BinaryReadSettings"
							}
						}
					},
					{
						"name": "ForEach1",
						"type": "ForEach",
						"dependsOn": [
							{
								"activity": "Get Metadata1",
								"dependencyConditions": [
									"Succeeded"
								]
							}
						],
						"userProperties": [],
						"typeProperties": {
							"items": {
								"value": "@activity('Get Metadata1').output.childitems",
								"type": "Expression"
							},
							"activities": [
								{
									"name": "Copy data1",
									"type": "Copy",
									"dependsOn": [],
									"policy": {
										"timeout": "7.00:00:00",
										"retry": 0,
										"retryIntervalInSeconds": 30,
										"secureOutput": false,
										"secureInput": false
									},
									"userProperties": [],
									"typeProperties": {
										"source": {
											"type": "BinarySource",
											"storeSettings": {
												"type": "AzureBlobStorageReadSettings",
												"recursive": false,
												"deleteFilesAfterCompletion": false
											},
											"formatSettings": {
												"type": "BinaryReadSettings",
												"compressionProperties": {
													"type": "ZipDeflateReadSettings",
													"preserveZipFileNameAsFolder": false
												}
											}
										},
										"sink": {
											"type": "BinarySink",
											"storeSettings": {
												"type": "AzureBlobStorageWriteSettings"
											}
										},
										"enableStaging": false
									},
									"inputs": [
										{
											"referenceName": "Binary1",
											"type": "DatasetReference",
											"parameters": {
												"filename": {
													"value": "@item().name",
													"type": "Expression"
												}
											}
										}
									],
									"outputs": [
										{
											"referenceName": "Binary2",
											"type": "DatasetReference",
											"parameters": {}
										}
									]
								}
							]
						}
					},
					{
						"name": "Copy data2",
						"type": "Copy",
						"dependsOn": [
							{
								"activity": "ForEach1",
								"dependencyConditions": [
									"Succeeded"
								]
							}
						],
						"policy": {
							"timeout": "7.00:00:00",
							"retry": 0,
							"retryIntervalInSeconds": 30,
							"secureOutput": false,
							"secureInput": false
						},
						"userProperties": [],
						"typeProperties": {
							"source": {
								"type": "DelimitedTextSource",
								"storeSettings": {
									"type": "AzureBlobStorageReadSettings",
									"recursive": true,
									"wildcardFolderPath": "output",
									"wildcardFileName": "*.csv",
									"enablePartitionDiscovery": false
								},
								"formatSettings": {
									"type": "DelimitedTextReadSettings"
								}
							},
							"sink": {
								"type": "AzureSqlSink"
							},
							"enableStaging": false,
							"translator": {
								"type": "TabularTranslator",
								"mappings": [
									{
										"source": {
											"name": "Name",
											"type": "String",
											"physicalType": "String"
										},
										"sink": {
											"name": "Name",
											"type": "String",
											"physicalType": "nvarchar"
										}
									},
									{
										"source": {
											"name": "Age",
											"type": "String",
											"physicalType": "String"
										},
										"sink": {
											"name": "Age",
											"type": "String",
											"physicalType": "nvarchar"
										}
									},
									{
										"source": {
											"name": "Gender",
											"type": "String",
											"physicalType": "String"
										},
										"sink": {
											"name": "Gender",
											"type": "String",
											"physicalType": "nvarchar"
										}
									}
								],
								"typeConversion": true,
								"typeConversionSettings": {
									"allowDataTruncation": true,
									"treatBooleanAsNumber": false
								}
							}
						},
						"inputs": [
							{
								"referenceName": "DelimitedText1",
								"type": "DatasetReference",
								"parameters": {}
							}
						],
						"outputs": [
							{
								"referenceName": "AzureSqlTable1",
								"type": "DatasetReference",
								"parameters": {}
							}
						]
					}
				],
				"annotations": []
			},
			"dependsOn": [
				"[concat(variables('factoryId'), '/datasets/Binary1')]",
				"[concat(variables('factoryId'), '/datasets/DelimitedText1')]",
				"[concat(variables('factoryId'), '/datasets/AzureSqlTable1')]",
				"[concat(variables('factoryId'), '/datasets/Binary2')]"
			]
		},
		{
			"name": "[concat(parameters('factoryName'), '/pipeline3')]",
			"type": "Microsoft.DataFactory/factories/pipelines",
			"apiVersion": "2018-06-01",
			"properties": {
				"activities": [
					{
						"name": "Execute Pipeline1",
						"type": "ExecutePipeline",
						"dependsOn": [],
						"userProperties": [],
						"typeProperties": {
							"pipeline": {
								"referenceName": "pipeline2",
								"type": "PipelineReference"
							},
							"waitOnCompletion": true,
							"parameters": {}
						}
					},
					{
						"name": "Web1",
						"type": "WebActivity",
						"dependsOn": [
							{
								"activity": "Execute Pipeline1",
								"dependencyConditions": [
									"Failed"
								]
							}
						],
						"policy": {
							"timeout": "7.00:00:00",
							"retry": 0,
							"retryIntervalInSeconds": 30,
							"secureOutput": false,
							"secureInput": false
						},
						"userProperties": [],
						"typeProperties": {
							"url": "https://prod-90.eastus.logic.azure.com:443/workflows/9c17a57885524fe4b7d4a31e38862692/triggers/manual/paths/invoke?api-version=2016-10-01&sp=%2Ftriggers%2Fmanual%2Frun&sv=1.0&sig=kcBNAQAJK0V9GLAZn-z03CfvtXlq4seZ-DtEeqgYb1E",
							"method": "POST",
							"headers": {},
							"body": {
								"value": "{\n\"PipelineName\":\"@{pipeline().Pipeline}\",\n\"Error Message\":\"@{activity('Execute Pipeline1').Error.Message}\"\n}",
								"type": "Expression"
							}
						}
					}
				],
				"annotations": []
			},
			"dependsOn": [
				"[concat(variables('factoryId'), '/pipelines/pipeline2')]"
			]
		}
	]
}